pollination/cumulative_radiation/__init__.py
pollination/cumulative_radiation/_cumulative_radiation.py
pollination/cumulative_radiation/_prepare_folder.py
pollination/cumulative_radiation/entry.py
pollination_cumulative_radiation-0.3.9.dist-info/LICENSE
pollination_cumulative_radiation-0.3.9.dist-info/METADATA
pollination_cumulative_radiation-0.3.9.dist-info/WHEEL
pollination_cumulative_radiation-0.3.9.dist-info/top_level.txt
pollination_cumulative_radiation-0.3.9.dist-info/RECORD
