Metadata-Version: 2.1
Name: pollination-cumulative-radiation
Version: 0.3.9
Summary: Cumulative Radiation recipe for Pollination.
Home-page: https://github.com/pollination/cumulative-radiation
Author: ladybug-tools
Author-email: info@ladybug.tools
Maintainer: mostapha, ladybug-tools
Maintainer-email: mostapha@ladybug.tools, info@ladybug.tools
License: PolyForm Shield License 1.0.0, https://polyformproject.org/wp-content/uploads/2020/06/PolyForm-Shield-1.0.0.txt
Project-URL: icon, https://raw.githubusercontent.com/ladybug-tools/artwork/master/icons_components/honeybee/png/radrecipe.png
Project-URL: docker, https://hub.docker.com/r/ladybugtools/honeybee-radiance
Keywords: honeybee,radiance,ladybug-tools,daylight,cumulative,radiation
License-File: LICENSE
Requires-Dist: pollination-honeybee-radiance (==0.22.41)
Requires-Dist: pollination-alias (==0.11.8)
Requires-Dist: pollination-path (==0.3.2)
Provides-Extra: viz
Requires-Dist: pollination-honeybee-display (>=0.1.11) ; extra == 'viz'
